gammath_spot/__init__.py
gammath_spot/bardgen_stock_news.py
gammath_spot/bardgen_tilib.py
gammath_spot/cgptgen_tilib.py
gammath_spot/gammath_backtesting.py
gammath_spot/gammath_bb_signals.py
gammath_spot/gammath_beta_signals.py
gammath_spot/gammath_get_stcktwts.py
gammath_spot/gammath_get_stocks_calendar.py
gammath_spot/gammath_get_stocks_data.py
gammath_spot/gammath_get_stocks_events_data.py
gammath_spot/gammath_get_stocks_financials.py
gammath_spot/gammath_get_stocks_history.py
gammath_spot/gammath_get_stocks_options_data.py
gammath_spot/gammath_get_stocks_summary.py
gammath_spot/gammath_gscores_history.py
gammath_spot/gammath_gui_app.py
gammath_spot/gammath_ihp_signals.py
gammath_spot/gammath_inshp_signals.py
gammath_spot/gammath_kf_signals.py
gammath_spot/gammath_lgstic_signals.py
gammath_spot/gammath_lpep.py
gammath_spot/gammath_macd_signals.py
gammath_spot/gammath_mfi_signals.py
gammath_spot/gammath_mi_scores.py
gammath_spot/gammath_mtpc.py
gammath_spot/gammath_news_sentiment.py
gammath_spot/gammath_ols_signals.py
gammath_spot/gammath_options_signals.py
gammath_spot/gammath_pbr_signals.py
gammath_spot/gammath_pdp.py
gammath_spot/gammath_pe_signals.py
gammath_spot/gammath_peg_signals.py
gammath_spot/gammath_price_signals.py
gammath_spot/gammath_qbs_signals.py
gammath_spot/gammath_reco_signals.py
gammath_spot/gammath_rnn_predictor.py
gammath_spot/gammath_rsi_signals.py
gammath_spot/gammath_si_charts.py
gammath_spot/gammath_spot_rl_gym_env.py
gammath_spot/gammath_stcktwts_signals.py
gammath_spot/gammath_stoch_signals.py
gammath_spot/gammath_stocks_analysis.py
gammath_spot/gammath_stocks_analyzer_and_scorer.py
gammath_spot/gammath_stocks_backtesting.py
gammath_spot/gammath_stocks_data_scraper.py
gammath_spot/gammath_stocks_gscores_historian.py
gammath_spot/gammath_stocks_pep.py
gammath_spot/gammath_stocks_screener.py
gammath_spot/gammath_tc.py
gammath_spot/gammath_utils.py
gammath_spot/version.py
gammath_spot/data/logo.png
gammath_spot-13.5.0.dist-info/LICENSE.txt
gammath_spot-13.5.0.dist-info/METADATA
gammath_spot-13.5.0.dist-info/WHEEL
gammath_spot-13.5.0.dist-info/entry_points.txt
gammath_spot-13.5.0.dist-info/top_level.txt
gammath_spot-13.5.0.dist-info/RECORD
