Metadata-Version: 2.1
Name: gammath_spot
Version: 13.5.0
Summary: Stock Price-Opining Toolset
Home-page: https://github.com/salylgw/gammath_spot.git
Author: Salyl Bhagwat
Author-email: salylgw@gmail.com
Classifier: Development Status :: 4 - Beta
Classifier: License :: OSI Approved :: GNU General Public License v3 (GPLv3)
Classifier: Programming Language :: Python :: 3.8
Classifier: Topic :: Office/Business :: Financial :: Investment
License-File: LICENSE.txt
Requires-Dist: numpy
Requires-Dist: pandas
Requires-Dist: pandas-datareader
Requires-Dist: yfinance
Requires-Dist: pykalman
Requires-Dist: statsmodels
Requires-Dist: matplotlib
Requires-Dist: scikit-learn
Requires-Dist: textblob
Requires-Dist: tensorflow
Requires-Dist: keras-tuner
Requires-Dist: gymnasium
